{
  "manifestVersion": "3.2",
  "proxies": [
    {
      "address": "0xB3dbD44477a7bcf253f2fA68eDb4be5aF2F2cA56",
      "txHash": "0xe67b95d8acc4a94682f92c35c9b01a5bce141dd02bff1c2241f762c58da18763",
      "kind": "uups"
    },
    {
      "address": "0x10827cC42a09D0BAD2d43134C69F0e776D853D85",
      "txHash": "0x10a0e1fc0dd520086fd90dc5a921032ff87512f9c2a4faf54692fe2297fe30a1",
      "kind": "uups"
    },
    {
      "address": "0x7e67bf96ADbf4a813DD7b0A3Ca3060a937018946",
      "txHash": "0x864df708570be07c98ea3d707f891689154659e6d0514195797e9e1b0a2a3e6d",
      "kind": "uups"
    }
  ],
  "impls": {
    "9ebb8f5792f60ce07f08bb16e421909311b544b0be92b8ef9ec8f8a7d8674c87": {
      "address": "0xaB44BE78499721b593a0f4BE2099b246e9C53B57",
      "txHash": "0x26200a441541bc8bb6236b43eed1c2e023540a0f4652f6cd01953fb65fc040ef",
      "layout": {
        "solcVersion": "0.8.28",
        "storage": [
          {
            "label": "llmBalance",
            "offset": 0,
            "slot": "0",
            "type": "t_mapping(t_address,t_uint256)",
            "contract": "LLMv1",
            "src": "contracts/LLMv1.sol:19"
          },
          {
            "label": "processedBatches",
            "offset": 0,
            "slot": "1",
            "type": "t_mapping(t_bytes32,t_bool)",
            "contract": "LLMv1",
            "src": "contracts/LLMv1.sol:21"
          },
          {
            "label": "authorizedProviders",
            "offset": 0,
            "slot": "2",
            "type": "t_mapping(t_address,t_bool)",
            "contract": "LLMv1",
            "src": "contracts/LLMv1.sol:23"
          },
          {
            "label": "defaultServiceProvider",
            "offset": 0,
            "slot": "3",
            "type": "t_address",
            "contract": "LLMv1",
            "src": "contracts/LLMv1.sol:25"
          },
          {
            "label": "__gap",
            "offset": 0,
            "slot": "4",
            "type": "t_array(t_uint256)50_storage",
            "contract": "LLMv1",
            "src": "contracts/LLMv1.sol:206"
          }
        ],
        "types": {
          "t_address": {
            "label": "address",
            "numberOfBytes": "20"
          },
          "t_bool": {
            "label": "bool",
            "numberOfBytes": "1"
          },
          "t_struct(InitializableStorage)73_storage": {
            "label": "struct Initializable.InitializableStorage",
            "members": [
              {
                "label": "_initialized",
                "type": "t_uint64",
                "offset": 0,
                "slot": "0"
              },
              {
                "label": "_initializing",
                "type": "t_bool",
                "offset": 8,
                "slot": "0"
              }
            ],
            "numberOfBytes": "32"
          },
          "t_struct(OwnableStorage)13_storage": {
            "label": "struct OwnableUpgradeable.OwnableStorage",
            "members": [
              {
                "label": "_owner",
                "type": "t_address",
                "offset": 0,
                "slot": "0"
              }
            ],
            "numberOfBytes": "32"
          },
          "t_uint64": {
            "label": "uint64",
            "numberOfBytes": "8"
          },
          "t_array(t_uint256)50_storage": {
            "label": "uint256[50]",
            "numberOfBytes": "1600"
          },
          "t_bytes32": {
            "label": "bytes32",
            "numberOfBytes": "32"
          },
          "t_mapping(t_address,t_bool)": {
            "label": "mapping(address => bool)",
            "numberOfBytes": "32"
          },
          "t_mapping(t_address,t_uint256)": {
            "label": "mapping(address => uint256)",
            "numberOfBytes": "32"
          },
          "t_mapping(t_bytes32,t_bool)": {
            "label": "mapping(bytes32 => bool)",
            "numberOfBytes": "32"
          },
          "t_uint256": {
            "label": "uint256",
            "numberOfBytes": "32"
          }
        },
        "namespaces": {
          "erc7201:openzeppelin.storage.Ownable": [
            {
              "contract": "OwnableUpgradeable",
              "label": "_owner",
              "type": "t_address",
              "src": "@openzeppelin/contracts-upgradeable/access/OwnableUpgradeable.sol:24",
              "offset": 0,
              "slot": "0"
            }
          ],
          "erc7201:openzeppelin.storage.Initializable": [
            {
              "contract": "Initializable",
              "label": "_initialized",
              "type": "t_uint64",
              "src": "@openzeppelin/contracts-upgradeable/proxy/utils/Initializable.sol:69",
              "offset": 0,
              "slot": "0"
            },
            {
              "contract": "Initializable",
              "label": "_initializing",
              "type": "t_bool",
              "src": "@openzeppelin/contracts-upgradeable/proxy/utils/Initializable.sol:73",
              "offset": 8,
              "slot": "0"
            }
          ]
        }
      }
    },
    "3e0aa9d8d245fe96d9616b74d743c48ee7922fa2e99717fbfba2fa01992fe46f": {
      "address": "0x5D0103393DDcD988867437233c197c6A38b23360",
      "txHash": "0x15eb75474faa428b174e3723aa85aa00c86f6fabea63ddb74085b0e2e9551d92",
      "layout": {
        "solcVersion": "0.8.28",
        "storage": [
          {
            "label": "_nextTokenId",
            "offset": 0,
            "slot": "0",
            "type": "t_uint256",
            "contract": "GenImNFTv4",
            "src": "contracts/GenImNFTv4.sol:20"
          },
          {
            "label": "mintPrice",
            "offset": 0,
            "slot": "1",
            "type": "t_uint256",
            "contract": "GenImNFTv4",
            "src": "contracts/GenImNFTv4.sol:23"
          },
          {
            "label": "_authorizedImageUpdaters",
            "offset": 0,
            "slot": "2",
            "type": "t_mapping(t_uint256,t_address)",
            "contract": "GenImNFTv4",
            "src": "contracts/GenImNFTv4.sol:27"
          },
          {
            "label": "_imageUpdated",
            "offset": 0,
            "slot": "3",
            "type": "t_mapping(t_uint256,t_bool)",
            "contract": "GenImNFTv4",
            "src": "contracts/GenImNFTv4.sol:30"
          },
          {
            "label": "_isListed",
            "offset": 0,
            "slot": "4",
            "type": "t_mapping(t_uint256,t_bool)",
            "contract": "GenImNFTv4",
            "src": "contracts/GenImNFTv4.sol:33"
          },
          {
            "label": "_whitelistedAgentWallets",
            "offset": 0,
            "slot": "5",
            "type": "t_mapping(t_address,t_bool)",
            "contract": "GenImNFTv4",
            "src": "contracts/GenImNFTv4.sol:37"
          },
          {
            "label": "__gap",
            "offset": 0,
            "slot": "6",
            "type": "t_array(t_uint256)48_storage",
            "contract": "GenImNFTv4",
            "src": "contracts/GenImNFTv4.sol:375"
          }
        ],
        "types": {
          "t_address": {
            "label": "address",
            "numberOfBytes": "20"
          },
          "t_array(t_uint256)dyn_storage": {
            "label": "uint256[]",
            "numberOfBytes": "32"
          },
          "t_bool": {
            "label": "bool",
            "numberOfBytes": "1"
          },
          "t_mapping(t_address,t_bool)": {
            "label": "mapping(address => bool)",
            "numberOfBytes": "32"
          },
          "t_mapping(t_address,t_mapping(t_address,t_bool))": {
            "label": "mapping(address => mapping(address => bool))",
            "numberOfBytes": "32"
          },
          "t_mapping(t_address,t_mapping(t_uint256,t_uint256))": {
            "label": "mapping(address => mapping(uint256 => uint256))",
            "numberOfBytes": "32"
          },
          "t_mapping(t_address,t_uint256)": {
            "label": "mapping(address => uint256)",
            "numberOfBytes": "32"
          },
          "t_mapping(t_uint256,t_address)": {
            "label": "mapping(uint256 => address)",
            "numberOfBytes": "32"
          },
          "t_mapping(t_uint256,t_string_storage)": {
            "label": "mapping(uint256 => string)",
            "numberOfBytes": "32"
          },
          "t_mapping(t_uint256,t_uint256)": {
            "label": "mapping(uint256 => uint256)",
            "numberOfBytes": "32"
          },
          "t_string_storage": {
            "label": "string",
            "numberOfBytes": "32"
          },
          "t_struct(ERC721EnumerableStorage)578_storage": {
            "label": "struct ERC721EnumerableUpgradeable.ERC721EnumerableStorage",
            "members": [
              {
                "label": "_ownedTokens",
                "type": "t_mapping(t_address,t_mapping(t_uint256,t_uint256))",
                "offset": 0,
                "slot": "0"
              },
              {
                "label": "_ownedTokensIndex",
                "type": "t_mapping(t_uint256,t_uint256)",
                "offset": 0,
                "slot": "1"
              },
              {
                "label": "_allTokens",
                "type": "t_array(t_uint256)dyn_storage",
                "offset": 0,
                "slot": "2"
              },
              {
                "label": "_allTokensIndex",
                "type": "t_mapping(t_uint256,t_uint256)",
                "offset": 0,
                "slot": "3"
              }
            ],
            "numberOfBytes": "128"
          },
          "t_struct(ERC721Storage)240_storage": {
            "label": "struct ERC721Upgradeable.ERC721Storage",
            "members": [
              {
                "label": "_name",
                "type": "t_string_storage",
                "offset": 0,
                "slot": "0"
              },
              {
                "label": "_symbol",
                "type": "t_string_storage",
                "offset": 0,
                "slot": "1"
              },
              {
                "label": "_owners",
                "type": "t_mapping(t_uint256,t_address)",
                "offset": 0,
                "slot": "2"
              },
              {
                "label": "_balances",
                "type": "t_mapping(t_address,t_uint256)",
                "offset": 0,
                "slot": "3"
              },
              {
                "label": "_tokenApprovals",
                "type": "t_mapping(t_uint256,t_address)",
                "offset": 0,
                "slot": "4"
              },
              {
                "label": "_operatorApprovals",
                "type": "t_mapping(t_address,t_mapping(t_address,t_bool))",
                "offset": 0,
                "slot": "5"
              }
            ],
            "numberOfBytes": "192"
          },
          "t_struct(ERC721URIStorageStorage)714_storage": {
            "label": "struct ERC721URIStorageUpgradeable.ERC721URIStorageStorage",
            "members": [
              {
                "label": "_tokenURIs",
                "type": "t_mapping(t_uint256,t_string_storage)",
                "offset": 0,
                "slot": "0"
              }
            ],
            "numberOfBytes": "32"
          },
          "t_struct(InitializableStorage)73_storage": {
            "label": "struct Initializable.InitializableStorage",
            "members": [
              {
                "label": "_initialized",
                "type": "t_uint64",
                "offset": 0,
                "slot": "0"
              },
              {
                "label": "_initializing",
                "type": "t_bool",
                "offset": 8,
                "slot": "0"
              }
            ],
            "numberOfBytes": "32"
          },
          "t_struct(OwnableStorage)13_storage": {
            "label": "struct OwnableUpgradeable.OwnableStorage",
            "members": [
              {
                "label": "_owner",
                "type": "t_address",
                "offset": 0,
                "slot": "0"
              }
            ],
            "numberOfBytes": "32"
          },
          "t_uint256": {
            "label": "uint256",
            "numberOfBytes": "32"
          },
          "t_uint64": {
            "label": "uint64",
            "numberOfBytes": "8"
          },
          "t_array(t_uint256)48_storage": {
            "label": "uint256[48]",
            "numberOfBytes": "1536"
          },
          "t_mapping(t_uint256,t_bool)": {
            "label": "mapping(uint256 => bool)",
            "numberOfBytes": "32"
          }
        },
        "namespaces": {
          "erc7201:openzeppelin.storage.Ownable": [
            {
              "contract": "OwnableUpgradeable",
              "label": "_owner",
              "type": "t_address",
              "src": "@openzeppelin/contracts-upgradeable/access/OwnableUpgradeable.sol:24",
              "offset": 0,
              "slot": "0"
            }
          ],
          "erc7201:openzeppelin.storage.ERC721Enumerable": [
            {
              "contract": "ERC721EnumerableUpgradeable",
              "label": "_ownedTokens",
              "type": "t_mapping(t_address,t_mapping(t_uint256,t_uint256))",
              "src": "@openzeppelin/contracts-upgradeable/token/ERC721/extensions/ERC721EnumerableUpgradeable.sol:21",
              "offset": 0,
              "slot": "0"
            },
            {
              "contract": "ERC721EnumerableUpgradeable",
              "label": "_ownedTokensIndex",
              "type": "t_mapping(t_uint256,t_uint256)",
              "src": "@openzeppelin/contracts-upgradeable/token/ERC721/extensions/ERC721EnumerableUpgradeable.sol:22",
              "offset": 0,
              "slot": "1"
            },
            {
              "contract": "ERC721EnumerableUpgradeable",
              "label": "_allTokens",
              "type": "t_array(t_uint256)dyn_storage",
              "src": "@openzeppelin/contracts-upgradeable/token/ERC721/extensions/ERC721EnumerableUpgradeable.sol:24",
              "offset": 0,
              "slot": "2"
            },
            {
              "contract": "ERC721EnumerableUpgradeable",
              "label": "_allTokensIndex",
              "type": "t_mapping(t_uint256,t_uint256)",
              "src": "@openzeppelin/contracts-upgradeable/token/ERC721/extensions/ERC721EnumerableUpgradeable.sol:25",
              "offset": 0,
              "slot": "3"
            }
          ],
          "erc7201:openzeppelin.storage.ERC721URIStorage": [
            {
              "contract": "ERC721URIStorageUpgradeable",
              "label": "_tokenURIs",
              "type": "t_mapping(t_uint256,t_string_storage)",
              "src": "@openzeppelin/contracts-upgradeable/token/ERC721/extensions/ERC721URIStorageUpgradeable.sol:26",
              "offset": 0,
              "slot": "0"
            }
          ],
          "erc7201:openzeppelin.storage.ERC721": [
            {
              "contract": "ERC721Upgradeable",
              "label": "_name",
              "type": "t_string_storage",
              "src": "@openzeppelin/contracts-upgradeable/token/ERC721/ERC721Upgradeable.sol:27",
              "offset": 0,
              "slot": "0"
            },
            {
              "contract": "ERC721Upgradeable",
              "label": "_symbol",
              "type": "t_string_storage",
              "src": "@openzeppelin/contracts-upgradeable/token/ERC721/ERC721Upgradeable.sol:30",
              "offset": 0,
              "slot": "1"
            },
            {
              "contract": "ERC721Upgradeable",
              "label": "_owners",
              "type": "t_mapping(t_uint256,t_address)",
              "src": "@openzeppelin/contracts-upgradeable/token/ERC721/ERC721Upgradeable.sol:32",
              "offset": 0,
              "slot": "2"
            },
            {
              "contract": "ERC721Upgradeable",
              "label": "_balances",
              "type": "t_mapping(t_address,t_uint256)",
              "src": "@openzeppelin/contracts-upgradeable/token/ERC721/ERC721Upgradeable.sol:34",
              "offset": 0,
              "slot": "3"
            },
            {
              "contract": "ERC721Upgradeable",
              "label": "_tokenApprovals",
              "type": "t_mapping(t_uint256,t_address)",
              "src": "@openzeppelin/contracts-upgradeable/token/ERC721/ERC721Upgradeable.sol:36",
              "offset": 0,
              "slot": "4"
            },
            {
              "contract": "ERC721Upgradeable",
              "label": "_operatorApprovals",
              "type": "t_mapping(t_address,t_mapping(t_address,t_bool))",
              "src": "@openzeppelin/contracts-upgradeable/token/ERC721/ERC721Upgradeable.sol:38",
              "offset": 0,
              "slot": "5"
            }
          ],
          "erc7201:openzeppelin.storage.Initializable": [
            {
              "contract": "Initializable",
              "label": "_initialized",
              "type": "t_uint64",
              "src": "@openzeppelin/contracts-upgradeable/proxy/utils/Initializable.sol:69",
              "offset": 0,
              "slot": "0"
            },
            {
              "contract": "Initializable",
              "label": "_initializing",
              "type": "t_bool",
              "src": "@openzeppelin/contracts-upgradeable/proxy/utils/Initializable.sol:73",
              "offset": 8,
              "slot": "0"
            }
          ]
        }
      }
    },
    "820ba084a21c361ebf29c2e4130fb960ce9eef9559ff0b6883424e2a5743fc1b": {
      "address": "0xf18E3901D91D8a08380E37A466E6F7f6AA4BD4a6",
      "txHash": "0xeeda6ce5c093bd5ca6a8d2a098faf8c71d02881433d7f1c400d3ac3f72884f29",
      "layout": {
        "solcVersion": "0.8.33",
        "storage": [
          {
            "label": "facilitatorWallet",
            "offset": 0,
            "slot": "0",
            "type": "t_address",
            "contract": "EIP3009SplitterV1",
            "src": "contracts/EIP3009SplitterV1.sol:82"
          },
          {
            "label": "fixedFee",
            "offset": 0,
            "slot": "1",
            "type": "t_uint256",
            "contract": "EIP3009SplitterV1",
            "src": "contracts/EIP3009SplitterV1.sol:87"
          },
          {
            "label": "__gap",
            "offset": 0,
            "slot": "2",
            "type": "t_array(t_uint256)50_storage",
            "contract": "EIP3009SplitterV1",
            "src": "contracts/EIP3009SplitterV1.sol:94"
          }
        ],
        "types": {
          "t_address": {
            "label": "address",
            "numberOfBytes": "20"
          },
          "t_bool": {
            "label": "bool",
            "numberOfBytes": "1"
          },
          "t_struct(InitializableStorage)86_storage": {
            "label": "struct Initializable.InitializableStorage",
            "members": [
              {
                "label": "_initialized",
                "type": "t_uint64",
                "offset": 0,
                "slot": "0"
              },
              {
                "label": "_initializing",
                "type": "t_bool",
                "offset": 8,
                "slot": "0"
              }
            ],
            "numberOfBytes": "32"
          },
          "t_struct(OwnableStorage)14_storage": {
            "label": "struct OwnableUpgradeable.OwnableStorage",
            "members": [
              {
                "label": "_owner",
                "type": "t_address",
                "offset": 0,
                "slot": "0"
              }
            ],
            "numberOfBytes": "32"
          },
          "t_uint64": {
            "label": "uint64",
            "numberOfBytes": "8"
          },
          "t_array(t_uint256)50_storage": {
            "label": "uint256[50]",
            "numberOfBytes": "1600"
          },
          "t_uint256": {
            "label": "uint256",
            "numberOfBytes": "32"
          }
        },
        "namespaces": {
          "erc7201:openzeppelin.storage.Ownable": [
            {
              "contract": "OwnableUpgradeable",
              "label": "_owner",
              "type": "t_address",
              "src": "@openzeppelin/contracts-upgradeable/access/OwnableUpgradeable.sol:24",
              "offset": 0,
              "slot": "0"
            }
          ],
          "erc7201:openzeppelin.storage.Initializable": [
            {
              "contract": "Initializable",
              "label": "_initialized",
              "type": "t_uint64",
              "src": "@openzeppelin/contracts-upgradeable/proxy/utils/Initializable.sol:69",
              "offset": 0,
              "slot": "0"
            },
            {
              "contract": "Initializable",
              "label": "_initializing",
              "type": "t_bool",
              "src": "@openzeppelin/contracts-upgradeable/proxy/utils/Initializable.sol:73",
              "offset": 8,
              "slot": "0"
            }
          ]
        }
      }
    }
  }
}
